capx/__init__.py
capx/example.py
capx/solver.py
capx-1.0.1.dist-info/licenses/LICENSE
capx-1.0.1.dist-info/METADATA
capx-1.0.1.dist-info/WHEEL
capx-1.0.1.dist-info/top_level.txt
capx-1.0.1.dist-info/RECORD
