Metadata-Version: 2.4
Name: capx
Version: 1.0.1
Summary: reCAPTCHA v2 Image Solver using YOLO and Selenium
Author-email: Mahdi Marjani <mahdi.marjani.dev@gmail.com>
License-Expression: MIT
Project-URL: Homepage, https://github.com/mahdi-marjani/capx
Project-URL: Documentation, https://github.com/mahdi-marjani/capx
Project-URL: Repository, https://github.com/mahdi-marjani/capx.git
Project-URL: Issues, https://github.com/mahdi-marjani/capx/issues
Requires-Python: >=3.8
License-File: LICENSE
Requires-Dist: selenium>=4.39.0
Requires-Dist: webdriver_manager>=4.0.2
Requires-Dist: capx-core>=1.0.1
Requires-Dist: capx-client>=1.0.1
Dynamic: license-file
